valorant/__init__.py
valorant/caller.py
valorant/client.py
valorant/lexicon.py
valorant/query.py
valorant/local/__init__.py
valorant/local/client.py
valorant/objects/__init__.py
valorant/objects/account.py
valorant/objects/content.py
valorant/objects/dto.py
valorant/objects/match.py
valorant/objects/platform.py
valorant/objects/player.py
valorant/objects/ranked.py
valorant-1.0.4.dist-info/LICENSE
valorant-1.0.4.dist-info/METADATA
valorant-1.0.4.dist-info/WHEEL
valorant-1.0.4.dist-info/top_level.txt
valorant-1.0.4.dist-info/RECORD
