Metadata-Version: 2.1
Name: valorant
Version: 1.0.4
Summary: Complete Python interface for the Valorant API. Works right out of the box!
Home-page: https://github.com/frissyn/valorant.py
Author: frissyn
License: MIT
Project-URL: Source Code, https://github.com/frissyn/valorant.py
Project-URL: Pull Requests, https://github.com/frissyn/valorant.py/pulls
Project-URL: Issue Tracker, https://github.com/frissyn/valorant.py/issues
Project-URL: Documentation, https://valorantpy.readthedocs.io/
Classifier: License :: OSI Approved :: MIT License
Classifier: Intended Audience :: Developers
Classifier: Operating System :: OS Independent
Classifier: Programming Language :: Python :: 3.8
Classifier: Programming Language :: Python :: 3.9
Classifier: Topic :: Software Development
Requires-Python: >=3.8.0
License-File: LICENSE
